opensicl/__init__.py
opensicl/main.py
opensicl/extractor/__init__.py
opensicl/extractor/base_extractor.py
opensicl/extractor/embedding_utils.py
opensicl/extractor/whisper.py
opensicl/retriever/__init__.py
opensicl/retriever/random_retriever.py
opensicl/retriever/topk_retriever.py
opensicl-0.1.0.dist-info/licenses/LICENSE
opensicl-0.1.0.dist-info/METADATA
opensicl-0.1.0.dist-info/WHEEL
opensicl-0.1.0.dist-info/top_level.txt
opensicl-0.1.0.dist-info/RECORD
